sarthiai/__init__.py
sarthiai/memory.py
sarthiai/memory_async.py
sarthiai/memory_models.py
sarthiai/utils.py
sarthiai-1.0.1.dist-info/LICENSE
sarthiai-1.0.1.dist-info/METADATA
sarthiai-1.0.1.dist-info/WHEEL
sarthiai-1.0.1.dist-info/top_level.txt
sarthiai-1.0.1.dist-info/RECORD
