Metadata-Version: 2.1
Name: sarthiai
Version: 1.0.1
Summary: Official Python SDK for SarthiAI API
Home-page: https://github.com/SarthiAI/SarthiAI-Python-SDK
Author: SarthiAI
Author-email: contact@sarthiai.com
License: UNKNOWN
Platform: UNKNOWN
Requires-Python: >=3.9.12
License-File: LICENSE
Requires-Dist: requests>=2.32.3
Requires-Dist: pydantic>=2.9.2
